{"categories":
  {
    "סרטים מדובבים": {"url": "https://raw.githubusercontent.com/SomeOneDudOrg/SomeOneDudOrgKodiRepo/master/HebDub.json", "fanart": "https://github.com/Jksp/jksp.repo/raw/master/resources/fanart.jpg", "thumb": "https://github.com/Jksp/jksp.repo/raw/master/resources/kids.thumb.png"},
    "TEST": {"url": "https://raw.githubusercontent.com/SomeOneDudOrg/SomeOneDudOrgKodiRepo/master/HebDub.json", "fanart": "https://github.com/Jksp/jksp.repo/raw/master/resources/fanart.jpg", "thumb": "https://github.com/Jksp/jksp.repo/blob/master/resources/kids.thumb.png?raw=true"}
  }
}
